Metadata-Version: 2.1
Name: utilbdb
Version: 0.0.1
Summary: A Util python package
Home-page: https://github.com/SmithSaurav/util_package
Author: smith
Author-email: smith@bdb.ai
Classifier: Programming Language :: Python :: 3
Classifier: License :: OSI Approved :: MIT License
Classifier: Operating System :: OS Independent
Requires-Python: >=3.6
License-File: license.txt
